jpl.edrn.ldap.utils-0.0.0-py3.10-nspkg.pth
jpl/edrn/ldap/utils/VERSION.txt
jpl/edrn/ldap/utils/__init__.py
jpl/edrn/ldap/utils/constants.py
jpl/edrn/ldap/utils/logging.py
jpl/edrn/ldap/utils/server.py
jpl/edrn/ldap/utils/users.py
jpl.edrn.ldap.utils-0.0.0.dist-info/LICENSE.md
jpl.edrn.ldap.utils-0.0.0.dist-info/METADATA
jpl.edrn.ldap.utils-0.0.0.dist-info/WHEEL
jpl.edrn.ldap.utils-0.0.0.dist-info/entry_points.txt
jpl.edrn.ldap.utils-0.0.0.dist-info/namespace_packages.txt
jpl.edrn.ldap.utils-0.0.0.dist-info/top_level.txt
jpl.edrn.ldap.utils-0.0.0.dist-info/zip-safe
jpl.edrn.ldap.utils-0.0.0.dist-info/RECORD
