Metadata-Version: 2.1
Name: jpl.edrn.ldap.utils
Version: 0.0.0
Summary: LDAP utilities for the EDRN Directory Service
Home-page: https://github.com/EDRN/jpl.edrn.ldap.utils
Author: Sean Kelly
Author-email: kelly@seankelly.biz
License: apache-2.0
Keywords: ldap directory cancer password
Classifier: Development Status :: 4 - Beta
Classifier: Environment :: Console
Classifier: Intended Audience :: Developers
Classifier: Intended Audience :: Healthcare Industry
Classifier: License :: OSI Approved :: Apache Software License
Classifier: Operating System :: OS Independent
Classifier: Programming Language :: Python :: 3
Classifier: Topic :: Scientific/Engineering :: Bio-Informatics
Requires-Python: >=3.9
License-File: LICENSE.md
Requires-Dist: python-ldap (~=3.4.3)
